sparta/__init__.py
sparta/delete.py
sparta/extract.py
sparta/load.py
sparta/logs.py
sparta/secret.py
sparta/transformation.py
sparta/validator.py
sparta/tests/__init__.py
sparta/tests/test_transformation.py
pysparta-0.5.6.dist-info/LICENSE
pysparta-0.5.6.dist-info/METADATA
pysparta-0.5.6.dist-info/WHEEL
pysparta-0.5.6.dist-info/top_level.txt
pysparta-0.5.6.dist-info/RECORD
