Metadata-Version: 2.1
Name: pysparta
Version: 0.5.6
Summary: Library to help ETL using pyspark
Home-page: https://github.com/jcpsantos/sparta
Author: Juan Caio
Author-email: juancaiops@gmail.com
License: GNU General Public License v2.0
Project-URL: Source code, https://github.com/jcpsantos/sparta
Project-URL: Documentation, https://jcpsantos.github.io/sparta/
Keywords: spark etl data sparta
Classifier: Intended Audience :: Developers
Classifier: Natural Language :: English
Classifier: Operating System :: OS Independent
Classifier: Topic :: Software Development :: Internationalization
Requires-Python: >= 3.7
License-File: LICENSE
Requires-Dist: azure-storage-blob>=12.12.0
Requires-Dist: boto3>=1.20.24
Requires-Dist: chispa>=0.9.2
Requires-Dist: pyspark>=3.2.1
Requires-Dist: pytest>=3.2.2
Requires-Dist: PyYAML>=6.0
Requires-Dist: smart-open>=6.0.0
Requires-Dist: delta-spark>=3.2.1
Provides-Extra: dev
Requires-Dist: pytest>=7.0.0; extra == "dev"
Requires-Dist: pytest-cov>=3.0.0; extra == "dev"
Requires-Dist: mypy>=0.942; extra == "dev"
Requires-Dist: types-pyyaml>=6.0.7; extra == "dev"
Requires-Dist: flake8>=4.0.1; extra == "dev"
Requires-Dist: docstr-coverage>=2.2.0; extra == "dev"
